origamist/__init__.py
origamist-0.0.1.dist-info/METADATA
origamist-0.0.1.dist-info/WHEEL
origamist-0.0.1.dist-info/RECORD
