Metadata-Version: 2.1
Name: origamist
Version: 0.0.1
Summary: 
Author: Kyle Kelley
Author-email: rgbkrk@gmail.com
Requires-Python: >=3.9,<4.0
Classifier: Programming Language :: Python :: 3
Classifier: Programming Language :: Python :: 3.9
Classifier: Programming Language :: Python :: 3.10
Classifier: Programming Language :: Python :: 3.11
Requires-Dist: aiocache (>=0.12.0,<0.13.0)
Requires-Dist: fastapi (>=0.95.0,<0.96.0)
Requires-Dist: nbclient (>=0.7.3,<0.8.0)
Requires-Dist: noteable-origami (>=0.0.23,<0.0.24)
Requires-Dist: pydantic (>=1.10.7,<2.0.0)
Requires-Dist: uvicorn (>=0.21.1,<0.22.0)
